google_nano_banana_mcp_server-1.0.0.dist-info/licenses/LICENSE
nano_banana_mcp/__init__.py
nano_banana_mcp/__main__.py
nano_banana_mcp/server.py
google_nano_banana_mcp_server-1.0.0.dist-info/METADATA
google_nano_banana_mcp_server-1.0.0.dist-info/WHEEL
google_nano_banana_mcp_server-1.0.0.dist-info/entry_points.txt
google_nano_banana_mcp_server-1.0.0.dist-info/top_level.txt
google_nano_banana_mcp_server-1.0.0.dist-info/RECORD
