Metadata-Version: 2.4
Name: google-nano-banana-mcp-server
Version: 1.0.0
Summary: 一个使用 Gemini 2.5 Flash Image 模型的图片生成和编辑 MCP 服务器
Home-page: https://github.com/example/nano-banana-mcp-server
Author: AI Assistant
Author-email: Nano Banana MCP <nano-banana-mcp@example.com>
Project-URL: Homepage, https://github.com/example/nano-banana-mcp-server
Project-URL: Bug Tracker, https://github.com/example/nano-banana-mcp-server/issues
Classifier: Programming Language :: Python :: 3
Classifier: License :: OSI Approved :: MIT License
Classifier: Operating System :: OS Independent
Requires-Python: >=3.8
License-File: LICENSE
Requires-Dist: fastmcp>=0.1.0
Requires-Dist: google-generativeai>=0.8.0
Requires-Dist: Pillow>=10.0.0
Requires-Dist: requests>=2.28.0
Dynamic: author
Dynamic: home-page
Dynamic: license-file
Dynamic: requires-python
